hybridkf/__init__.py
hybridkf/main.py
hybridkf-1.0.42.dist-info/LICENSE
hybridkf-1.0.42.dist-info/METADATA
hybridkf-1.0.42.dist-info/WHEEL
hybridkf-1.0.42.dist-info/top_level.txt
hybridkf-1.0.42.dist-info/RECORD
