Metadata-Version: 2.1
Name: hybridkf
Version: 1.0.42
Summary: An advanced implementation of the Kalman filter that handles and processes (pragmatic) continuous time-model state observations with discrete time-measurements for state estimation.
Home-page: https://github.com/akain0/hybridkf
Author: akain0
Classifier: Programming Language :: Python :: 3
Classifier: License :: OSI Approved :: MIT License
Classifier: Operating System :: OS Independent
Requires-Python: >=3.6
License-File: LICENSE
Requires-Dist: numpy
Requires-Dist: scipy
Requires-Dist: matplotlib
